{
  "device_address": "SEU:ENDERECO:BLE:AQUI",
  "device_name": "Wy Glass",
  "firmware": "LNJ-W03",
  "notify_char_uuid": "0000ff03-0000-1000-8000-00805f9b34fb",
  "actions_enabled": true,
  "battery_low_threshold": 20,
  "credentials": {
    "groq_api_key": "SUA_CHAVE_GROQ_AQUI",
    "tavily_api_key": "SUA_CHAVE_TAVILY_AQUI",
    "google_api_key": "SUA_CHAVE_GEMINI_AQUI"
  },
  "passive_listening": {
    "enabled": false,
    "clap_detection": {
      "enabled": false,
      "threshold_rms": 4000,
      "max_duration_ms": 120,
      "pair_window_ms": [150, 700],
      "gesture": "button1_single"
    }
  },
  "gestures": {
    "button1_single": {
      "label": "Botão 1 · Jarvis (headless, unificado)",
      "action": "open_jarvis_agent",
      "params": {
        "session_id": "wyglass",
        "user_name": "SEU_NOME_AQUI",
        "user_role": "sua atividade/papel",
        "tts_model": "pt_BR-faber-medium.onnx",
        "max_duration_seconds": 15,
        "silence_duration_seconds": 1,
        "silence_threshold": 400
      },
      "reliability": "high"
    },
    "button2_single": {
      "label": "Botão 2 · Encerrar conversa",
      "action": "stop_conversation",
      "params": {
        "farewell_text": "Até mais!",
        "tts_model": "pt_BR-faber-medium.onnx"
      },
      "reliability": "high"
    },
    "button1_double": {
      "label": "Botão 1 duplo · Jarvis (Groq, conversa contínua)",
      "action": "open_jarvis_agent",
      "params": {
        "session_id": "wyglass",
        "user_name": "SEU_NOME_AQUI",
        "user_role": "sua atividade/papel",
        "tts_model": "pt_BR-faber-medium.onnx",
        "max_duration_seconds": 15,
        "silence_duration_seconds": 1,
        "silence_threshold": 400,
        "conversation_mode": true
      },
      "reliability": "high"
    },
    "button2_double": {
      "label": "Botão 2 duplo · Abrir dashboard",
      "action": "open_dashboard",
      "params": {},
      "reliability": "high"
    }
  }
}
